orbit_framework/__init__.py
orbit_framework/devices.py
orbit_framework/index.py
orbit_framework/lcdcharset.py
orbit_framework/messaging.py
orbit_framework/setup.py
orbit_framework/tools.py
orbit_framework/components/__init__.py
orbit_framework/components/common.py
orbit_framework/components/lcd.py
orbit_framework/components/remoteswitch.py
orbit_framework/components/remoteswitch_v2.py
orbit_framework/components/timer.py
orbit_framework/jobs/__init__.py
orbit_framework/jobs/apps.py
orbit_framework/jobs/services.py
orbit_framework-0.2.0.dist-info/METADATA
orbit_framework-0.2.0.dist-info/WHEEL
orbit_framework-0.2.0.dist-info/top_level.txt
orbit_framework-0.2.0.dist-info/RECORD
