Metadata-Version: 2.1
Name: orbit_framework
Version: 0.2.0
Summary: Ein Python-Framework für robuste TinkerForge-Anwendungen
Home-page: http://mastersign.github.io/orbit/
Author: Tobias Kiertscher
Author-email: dev@mastersign.de
License: LGPL-3.0
Keywords: TinkerForge orbit framework
Classifier: License :: OSI Approved :: GNU Lesser General Public License v3 (LGPLv3)
Classifier: Programming Language :: Python
Classifier: Intended Audience :: Developers
Classifier: Natural Language :: German
Classifier: Topic :: Home Automation
Classifier: Topic :: Games/Entertainment
Requires-Dist: tinkerforge >=2.1.0
